{"42":"Golden Lantern '21","32":"Season 1","A":"Any","53":"Fornax","9":"Champion 3","23":"RL Beach Blast","13":"Overdrive","19":"Spring Fever","40":"Golden Pumpkin '19","41":"Golden Pumpkin '20","36":"Golden Lantern '19","59":"Golden Moon '23","22":"Impact","21":"Triumph","52":"Golden Moon","30":"Ignition","51":"Bonus Gift","27":"Totally Awesome","50":"Golden Gift '21","60":"Golden Toolkit","10":"Champion 4","46":"Auriga","25":"Zephyr","6":"Accelerator","26":"Ferocity","54":"Golden Gift Basket '22","29":"Revival","61":"Golden Egg '23","11":"Turbo","18":"Victory","2":"Golden Pumpkin '18","38":"Golden Egg '19","14":"Haunted Hallows","35":"Non-Crate","37":"Golden Egg '20","34":"Golden Gift '20","31":"Momentum","43":"Golden Gift '18","12":"Player's Choice","45":"Select Favorites","28":"Vindicator","5":"Velocity","3":"Champion 1","8":"Champion 2","49":"Dorado","39":"Golden Egg '18","56":"Golden Egg '22","1":"Elevation","57":"Golden Pumpkin '22","33":"Season 2","55":"Select Favorites 2","58":"Golden Gift '22","7":"Nitro","16":"Secret Santa","44":"Golden Gift '19"}